tromero_tailor/__init__.py
tromero_tailor/tromero_requests.py
tromero_tailor/tromero_utils.py
tromero_tailor/wrapper.py
tromero_tailor-0.0.24.dist-info/METADATA
tromero_tailor-0.0.24.dist-info/WHEEL
tromero_tailor-0.0.24.dist-info/top_level.txt
tromero_tailor-0.0.24.dist-info/RECORD
