Metadata-Version: 2.1
Name: tromero_tailor
Version: 0.0.24
Summary: A short description of your package
Home-page: http://yourpackagehomepage.com
Author: Tromero
Author-email: tadhg.amin@tromero.ai
License: MIT
Classifier: Programming Language :: Python :: 3
Classifier: License :: OSI Approved :: MIT License
Classifier: Operating System :: OS Independent
Requires-Python: >=3.6
Requires-Dist: annotated-types ==0.6.0
Requires-Dist: anyio ==4.3.0
Requires-Dist: certifi ==2024.2.2
Requires-Dist: charset-normalizer ==3.3.2
Requires-Dist: distro ==1.9.0
Requires-Dist: h11 ==0.14.0
Requires-Dist: httpcore ==1.0.5
Requires-Dist: httpx ==0.27.0
Requires-Dist: idna ==3.6
Requires-Dist: openai ==1.16.1
Requires-Dist: pydantic ==2.6.4
Requires-Dist: pydantic-core ==2.16.3
Requires-Dist: requests ==2.31.0
Requires-Dist: setuptools ==69.2.0
Requires-Dist: sniffio ==1.3.1
Requires-Dist: tqdm ==4.66.2
Requires-Dist: typing-extensions ==4.10.0
Requires-Dist: urllib3 ==2.2.1
